[{"header":"Components","description":"<p>Components are designed UI elements. Each component has its own React component,\nimportable from <code>src/scripts/components</code>.</p>\n","deprecated":false,"experimental":false,"reference":"Components","referenceNumber":"1","referenceURI":"","weight":0,"markup":"","source":{"filename":"components/_index.scss","path":"src/styles/components/_index.scss","line":1},"modifiers":[],"parameters":[],"sections":{}},{"header":"Buttons","description":"<p>Use buttons to signal actions.</p>\n<p><strong>Accessibility</strong></p>\n<ul>\n<li>Buttons should display a visible focus state when users tab to them.</li>\n<li>Avoid using <code>&lt;div&gt;</code> or <code>&lt;img&gt;</code> tags to create buttons. Screen readers don&#39;t automatically know either is a usable button.</li>\n<li>When styling links to look like buttons, remember that screen readers handle links slightly differently than they do buttons. Pressing the Space key triggers a button, but pressing the Enter key triggers a link.</li>\n</ul>\n","deprecated":false,"experimental":false,"reference":"Components.buttons","referenceNumber":"1.1","referenceURI":"","weight":0,"markup":"","source":{"filename":"components/button.scss","path":"src/styles/components/button.scss","line":4},"modifiers":[],"parameters":[],"sections":{}},{"header":"CSS API","description":"","deprecated":false,"experimental":false,"reference":"Components.buttons.css","referenceNumber":"1.1.1","referenceURI":"","weight":0,"markup":"<a href=\"#\" class=\"hc-c-button {{modifier_class}}\">Link text</a>\n<button type=\"button\" class=\"hc-c-button {{modifier_class}}\" {{:modifier}}>Button label</button>","source":{"filename":"components/button.scss","path":"src/styles/components/button.scss","line":17},"modifiers":[{"name":".hc-c-button--primary","description":"The primary call-to-action","className":""}],"parameters":[],"sections":{}},{"header":"JavaScript API","description":"<p>TODO:\nDocument the <code>Button</code> component.</p>\n\n","deprecated":false,"experimental":false,"reference":"Components.buttons.js","referenceNumber":"1.1.2","referenceURI":"","weight":0,"markup":"","source":{"filename":"components/button.scss","path":"src/styles/components/button.scss","line":61},"modifiers":[],"parameters":[],"sections":{},"reactExample":"ButtonExample"}]